fromchaos/__init__.py
fromchaos/fromchaos.py
fromchaos-0.0.10.dist-info/METADATA
fromchaos-0.0.10.dist-info/WHEEL
fromchaos-0.0.10.dist-info/top_level.txt
fromchaos-0.0.10.dist-info/RECORD
