Metadata-Version: 2.1
Name: fromchaos
Version: 0.0.10
Summary: A python library for extracting organized data out of chaos using large-language-models (LLMs) like ChatGPT.
Home-page: https://github.com/ryderdamen/fromchaos
Author: Ryder Damen
Author-email: dev@ryderdamen.com
Classifier: Development Status :: 3 - Alpha
Classifier: Intended Audience :: Developers
Classifier: License :: OSI Approved :: MIT License
Classifier: Programming Language :: Python :: 3.8
Requires-Python: >=3.8
Requires-Dist: openai (==1.4.0)
Requires-Dist: tenacity (==8.2.2)
Requires-Dist: google-generativeai (==0.3.1)
